{"stats":{"minecraft:killed":{"minecraft:sheep":3,"minecraft:donkey":2,"minecraft:creeper":11},"minecraft:picked_up":{"minecraft:brown_wool":1,"minecraft:gunpowder":3,"minecraft:mutton":3,"minecraft:white_wool":1},"minecraft:mined":{"minecraft:grass":2},"minecraft:custom":{"minecraft:time_since_rest":10664,"minecraft:crouch_one_cm":161,"minecraft:play_time":10664,"minecraft:sprint_one_cm":17555,"minecraft:walk_one_cm":17658,"minecraft:sneak_time":178,"minecraft:mob_kills":17,"minecraft:aviate_one_cm":1814,"minecraft:jump":61,"minecraft:damage_dealt":80,"minecraft:leave_game":1,"minecraft:time_since_death":10664,"minecraft:total_world_time":10664,"minecraft:fly_one_cm":78797},"minecraft:used":{"minecraft:creeper_spawn_egg":13,"minecraft:brown_wool":2,"mutantmonsters:endersoul_hand":5,"minecraft:zombie_spawn_egg":1}},"DataVersion":3465}