{
  "minecraft:nether/obtain_crying_obsidian": {
    "criteria": {
      "crying_obsidian": "2025-01-02 21:20:34 +0000"
    },
    "done": true
  },
  "minecraft:recipes/decorations/lantern": {
    "criteria": {
      "has_iron_nugget": "2025-01-02 21:20:05 +0000"
    },
    "done": true
  },
  "minecraft:recipes/misc/gold_nugget_from_smelting": {
    "criteria": {
      "has_golden_leggings": "2025-01-02 21:20:06 +0000"
    },
    "done": true
  },
  "minecraft:recipes/tools/flint_and_steel": {
    "criteria": {
      "has_obsidian": "2025-01-02 21:20:02 +0000"
    },
    "done": true
  },
  "minecraft:recipes/decorations/respawn_anchor": {
    "criteria": {
      "has_obsidian": "2025-01-02 21:20:34 +0000"
    },
    "done": true
  },
  "minecraft:recipes/misc/gold_nugget_from_blasting": {
    "criteria": {
      "has_golden_leggings": "2025-01-02 21:20:06 +0000"
    },
    "done": true
  },
  "minecraft:story/form_obsidian": {
    "criteria": {
      "obsidian": "2025-01-02 21:20:02 +0000"
    },
    "done": true
  },
  "minecraft:recipes/decorations/crafting_table": {
    "criteria": {
      "unlock_right_away": "2025-01-02 21:11:08 +0000"
    },
    "done": true
  },
  "minecraft:recipes/decorations/chain": {
    "criteria": {
      "has_iron_nugget": "2025-01-02 21:20:05 +0000"
    },
    "done": true
  },
  "mowziesmobs:root": {
    "criteria": {
      "custom_test_name": "2025-01-02 21:11:08 +0000"
    },
    "done": true
  },
  "minecraft:adventure/adventuring_time": {
    "criteria": {
      "minecraft:forest": "2025-01-02 21:11:08 +0000",
      "minecraft:plains": "2025-01-02 21:12:59 +0000"
    },
    "done": false
  },
  "minecraft:recipes/decorations/enchanting_table": {
    "criteria": {
      "has_obsidian": "2025-01-02 21:20:02 +0000"
    },
    "done": true
  },
  "minecraft:recipes/misc/nether_brick": {
    "criteria": {
      "has_netherrack": "2025-01-02 21:20:00 +0000"
    },
    "done": true
  },
  "cataclysm:root": {
    "criteria": {
      "custom_test_name": "2025-01-02 21:11:08 +0000"
    },
    "done": true
  },
  "minecraft:recipes/misc/iron_ingot_from_nuggets": {
    "criteria": {
      "has_iron_nugget": "2025-01-02 21:20:05 +0000"
    },
    "done": true
  },
  "DataVersion": 3465
}